nonebot_plugin_sanyao-0.3.1.dist-info/METADATA
nonebot_plugin_sanyao-0.3.1.dist-info/WHEEL
nonebot_plugin_sanyao-0.3.1.dist-info/entry_points.txt
nonebot_plugin_sanyao-0.3.1.dist-info/licenses/LICENSE
nonebot_plugin_sanyao/__init__.py
nonebot_plugin_sanyao/__main__.py
nonebot_plugin_sanyao/config.py
nonebot_plugin_sanyao/util/format_results.py
nonebot_plugin_sanyao/util/main.py
nonebot_plugin_sanyao/util/paipan.py
nonebot_plugin_sanyao/util/sanyaoyi.py
nonebot_plugin_sanyao-0.3.1.dist-info/RECORD
