Metadata-Version: 2.1
Name: nonebot-plugin-sanyao
Version: 0.3.1
Summary: 三爻易数排盘
Author-Email: afterow <afterow@163.com>
License: MIT License
Classifier: Framework :: Pydantic
Classifier: License :: OSI Approved :: MIT License
Classifier: Programming Language :: Python :: 3
Classifier: Programming Language :: Python :: 3 :: Only
Classifier: Programming Language :: Python :: 3.10
Classifier: Programming Language :: Python :: 3.11
Classifier: Natural Language :: Chinese (Simplified)
Project-URL: Homepage, https://github.com/afterow/nonebot-plugin-sanyao
Project-URL: Bug Tracker, https://github.com/afterow/nonebot-plugin-sanyao/issues
Requires-Python: <4.0,>=3.10
Requires-Dist: cnlunar
Requires-Dist: nonebot2
